gotohuman/__init__.py
gotohuman/_version.py
gotohuman/gotohuman.py
gotohuman-0.1.8.dist-info/licenses/LICENSE
gotohuman-0.1.8.dist-info/METADATA
gotohuman-0.1.8.dist-info/WHEEL
gotohuman-0.1.8.dist-info/top_level.txt
gotohuman-0.1.8.dist-info/RECORD
