Metadata-Version: 2.4
Name: gotohuman
Version: 0.1.8
Summary: Python SDK for gotoHuman
Home-page: https://gotohuman.com
Author: gotoHuman
Author-email: hello@gotohuman.com
License: MIT
Project-URL: Documentation, https://docs.gotohuman.com/
Project-URL: Twitter, https://twitter.com/gotohuman
Keywords: gotohuman ai agents llm automation human-in-the-loop
Requires-Python: >=3.8
License-File: LICENSE
Requires-Dist: requests
Dynamic: author
Dynamic: author-email
Dynamic: description
Dynamic: description-content-type
Dynamic: home-page
Dynamic: keywords
Dynamic: license
Dynamic: license-file
Dynamic: project-url
Dynamic: requires-dist
Dynamic: requires-python
Dynamic: summary
